open_notation.py
open_notation-0.0.1.dist-info/METADATA
open_notation-0.0.1.dist-info/WHEEL
open_notation-0.0.1.dist-info/top_level.txt
open_notation-0.0.1.dist-info/RECORD
