Metadata-Version: 2.1
Name: open-notation
Version: 0.0.1
Summary: YAML-based music notation
Author-email: Alexander Rodionov <tandav@tandav.me>
Project-URL: source, https://gitlab.tandav.me/bhairava/open-notation
Project-URL: issues, https://gitlab.tandav.me/bhairava/open-notation/-/issues
Project-URL: release notes, https://gitlab.tandav.me/bhairava/open-notation/-/releases
Requires-Python: >=3.10
Provides-Extra: dev
Requires-Dist: bumpver ; extra == 'dev'
Requires-Dist: pre-commit ; extra == 'dev'
Requires-Dist: pytest ; extra == 'dev'
